MANIFEST.in
README.rst
changelog.rst
setup.cfg
setup.py
Hooover.egg-info/PKG-INFO
Hooover.egg-info/SOURCES.txt
Hooover.egg-info/dependency_links.txt
Hooover.egg-info/requires.txt
Hooover.egg-info/top_level.txt
hooover/__init__.py
hooover/exceptions.py
hooover/handlers.py
hooover/hooover_sample.py
hooover/input.py
hooover/session.py
hooover/utils.py