Metadata-Version: 1.0
Name: Hooover
Version: 0.0.1
Summary: Library for logging to Loggly from within Python webapps
Home-page: https://bitbucket.org/juztin/hooover
Author: Hoover: Mike Blume, Hooover: Justin Wilson
Author-email: juztinwilzon@gmail.com
License: UNKNOWN
Platform: UNKNOWN
